requirements.txt
setup.py
django_rss_link_view/__init__.py
django_rss_link_view/views.py
django_rss_link_view.egg-info/PKG-INFO
django_rss_link_view.egg-info/SOURCES.txt
django_rss_link_view.egg-info/dependency_links.txt
django_rss_link_view.egg-info/requires.txt
django_rss_link_view.egg-info/top_level.txt