Metadata-Version: 2.1
Name: django-rss-link-view
Version: 2020.7.1
Summary: Django rss link view mixin
Home-page: https://github.com/andrewp-as-is/django-rss-link-view.py
License: Unlicense
Keywords: django rss
Platform: UNKNOWN
Classifier: Framework :: Django
Classifier: License :: Public Domain
Classifier: Operating System :: OS Independent
Classifier: Programming Language :: Python :: 3
